arango3_doc_manager-0.1.4.data/scripts/connector_arango_auth
arango3_doc_manager-0.1.4.dist-info/RECORD
arango3_doc_manager-0.1.4.dist-info/metadata.json
arango3_doc_manager-0.1.4.dist-info/METADATA
arango3_doc_manager-0.1.4.dist-info/top_level.txt
arango3_doc_manager-0.1.4.dist-info/WHEEL
arango3_doc_manager-0.1.4.dist-info/DESCRIPTION.rst
mongo_connector/__init__.py
mongo_connector/doc_managers/arango3_doc_manager.py
mongo_connector/doc_managers/__init__.py
