Metadata-Version: 2.0
Name: arango3-doc-manager
Version: 0.1.4
Summary: Arango3 plugin for mongo-connector
Home-page: https://github.com/Innoplexus-Consulting-Services/arango3-doc-manager.git
Author: Innoplexus
Author-email: prashant.patil@innoplexus.com
License: MIT License
Keywords: mongo-connector,mongodb,arango,arangodb
Platform: any
Classifier: Development Status :: 4 - Beta
Classifier: Intended Audience :: Developers
Classifier: Programming Language :: Python :: 2.6
Classifier: Programming Language :: Python :: 2.7
Classifier: Programming Language :: Python :: 3.3
Classifier: Programming Language :: Python :: 3.4
Classifier: Programming Language :: Python :: 3.5
Classifier: Topic :: Database
Classifier: Topic :: Software Development :: Libraries :: Python Modules
Classifier: Operating System :: Unix
Classifier: Operating System :: MacOS :: MacOS X
Requires-Dist: mongo-connector (>=2.5.0)
Requires-Dist: python-arango (>=3.12.1)
